abstract_instrument_interface/__init__.py
abstract_instrument_interface/abstract_classes.py
abstract_instrument_interface/ramp.py
abstract_instrument_interface/graphics/pause.png
abstract_instrument_interface/graphics/play.png
abstract_instrument_interface/graphics/refresh.png
abstract_instrument_interface/graphics/stop.png
abstract_instrument_interface-0.10.dist-info/METADATA
abstract_instrument_interface-0.10.dist-info/WHEEL
abstract_instrument_interface-0.10.dist-info/top_level.txt
abstract_instrument_interface-0.10.dist-info/RECORD
