Metadata-Version: 2.1
Name: abstract-instrument-interface
Version: 0.10
Summary: This package contains abstract classes for interfaces and GUIs which are used by all instruments compatible with Ergastirio
Home-page: https://github.com/MicheleCotrufo/
Author: Michele Cotrufo
Author-email: michele.cotrufo@gmail.com
License: MIT
Requires-Dist: PyQt5 (>=5.15.6)
Requires-Dist: typing-extensions
